{"noMoreComments": true, "cursorEnd": 0, "id": "1259212", "comments": [{"postBy": {"location": "", "utc": 1431594669000, "level": 0, "avatar": "http://filestoresg1.beetalkmobile.com:8081/file/-5152039906436344820", "name": "Min"}, "content": "", "urls": [], "replies": {"first": [], "last": [], "noMoreReplies": true}, "images": ["http://filestoresg1.beetalkmobile.com:8081/file/d0e9949caa6c02cff84b2e489c0ad8db", "http://filestoresg1.beetalkmobile.com:8081/file/ce1e08a6a73f5a145981fae91df41c22", "http://filestoresg1.beetalkmobile.com:8081/file/94729159c97849bb0e33fe3537baa015", "http://filestoresg1.beetalkmobile.com:8081/file/0a2ea352e5ebc00ba948c221bc7080ed", "http://filestoresg1.beetalkmobile.com:8081/file/d49b1843e010764d365724ecf933f93a", "http://filestoresg1.beetalkmobile.com:8081/file/9de5f8a138ea7a1858bcda3d595c46db"], "id": 11215811}, {"postBy": {"location": "", "utc": 1431594759000, "level": 0, "avatar": "http://filestoresg1.beetalkmobile.com:8081/file/-5152039906436344820", "name": "Min"}, "content": "", "urls": [], "replies": {"first": [], "last": [], "noMoreReplies": true}, "images": ["http://filestoresg1.beetalkmobile.com:8081/file/d596d0190da2505b0f2f8439218b0afc", "http://filestoresg1.beetalkmobile.com:8081/file/47e43e4d59ce90aabc589b89eab6f9b3", "http://filestoresg1.beetalkmobile.com:8081/file/3caa848f5191c97c86eecb6d0978b776", "http://filestoresg1.beetalkmobile.com:8081/file/7104f02be239d6ace3f506eeb8cc464a", "http://filestoresg1.beetalkmobile.com:8081/file/f53f87a44fd7b25ed704285ce6116405", "http://filestoresg1.beetalkmobile.com:8081/file/9ab9e252a9906654fb64c45ac29b157e"], "id": 11215912}, {"postBy": {"location": "\u65b0\u5317\u5e02\u00b7\u53f0\u7063", "utc": 1431597468000, "level": 0, "avatar": "http://filestoresg1.beetalkmobile.com:8081/file/6971269867253827239", "name": "\u5c0f\u9716"}, "content": "\u592a\u9592\u554a\u90a3\u5230\u9019\u88e1\u653e", "urls": [], "replies": {"first": [], "last": [], "noMoreReplies": true}, "images": [], "id": 11218401}, {"postBy": {"location": "\u6843\u5712\u5e02\u00b7\u53f0\u7063", "utc": 1431602199000, "level": 0, "avatar": "http://filestoresg1.beetalkmobile.com:8081/file/-1143310672401572756", "name": "SSS\u7d1a\u98df\u5c4d\u9b3c \u4ee3\u865f\uff1a\u8708\u86a3"}, "content": "\u771f\u662f\u500b\u9ad8\u624b<br />\u6211\u6230\u9b25\u529b\u53ea\u67096000<br />\u4f60\u7684\u81f3\u5c11\u4e00\u842c\u4ee5\u4e0a!<br />", "urls": [], "replies": {"first": [{"content": "\u8a87\u5f35\u4e86\u54c8\u54c8\u54c8", "reply": "", "id": 7233808, "name": "Min"}], "last": [], "noMoreReplies": true}, "images": [], "id": 11222734}]}
