{"noMoreComments": true, "cursorEnd": 0, "id": "1224383", "comments": [{"postBy": {"location": "\u5c4f\u6771\u7e23\u00b7\u53f0\u7063", "utc": 1431192266000, "level": 0, "avatar": "http://filestoresg1.beetalkmobile.com:8081/file/2", "name": "User blocked"}, "content": "\u5e25\u6c23", "urls": [], "replies": {"first": [{"content": "\u611f\u8b1d\u5566\ud83d\ude1a", "reply": "", "id": 7045214, "name": "\u97a5"}], "last": [], "noMoreReplies": true}, "images": [], "id": 10872596}, {"postBy": {"location": "\u53f0\u4e2d\u5e02\u00b7\u53f0\u7063", "utc": 1431192984000, "level": 0, "avatar": "http://filestoresg1.beetalkmobile.com:8081/file/3267747459501411835", "name": "\u7fd4\u7433Tina"}, "content": "\u5f88\u5e25", "urls": [], "replies": {"first": [{"content": "\ud83d\ude01\ud83d\ude01\ud83d\ude01\u263a\ufe0f\u263a\ufe0f", "reply": "", "id": 7045231, "name": "\u97a5"}], "last": [], "noMoreReplies": true}, "images": [], "id": 10873411}]}
