{"noMoreComments": true, "cursorEnd": 0, "id": "1945471", "comments": [{"postBy": {"location": "\u5c4f\u6771\u7e23\u00b7\u53f0\u7063", "utc": 1440000420000, "level": 0, "avatar": "http://filestoresg1.beetalkmobile.com:8081/file/1911904498178782096", "name": "\u93ae"}, "content": "\u5e36\u53f2\u8fea\u5947\u53bb\u653e\u9583\u55ce\uff1f", "urls": [], "replies": {"first": [{"content": "\u53ef\u4ee5\u7684\u8a71\uff0c\u563f\u55b2\uff01\uff01", "reply": "", "id": 11707987, "name": "\ud83c\udf6c\u53f2\u8fea\u5947\u6ce1\u6ce1\u5152\ud83c\udf6c"}, {"content": "\u7576\u7136\u53ef\u4ee5\u554a\uff01", "reply": "\ud83c\udf6c\u53f2\u8fea\u5947\u6ce1\u6ce1\u5152\ud83c\udf6c", "id": 11708034, "name": "\u93ae"}], "last": [], "noMoreReplies": true}, "images": [], "id": 18456831}, {"postBy": {"location": "", "utc": 1440026177000, "level": 0, "avatar": "http://filestoresg1.beetalkmobile.com:8081/file/-8541384552571774134", "name": "Sun"}, "content": "\u5f88\u597d  \uff01\uff01<br /><br />\u5c31\u9019\u6a23\u505a\u2026\u2026<br /><br />\u6211\u4e5f\u5e36\u6211\u5bb6\u5c0f\u718a\u53bb\u559d\u5496\u5561\u597d\u4e86", "urls": [], "replies": {"first": [{"content": "\u5f88\u53ef\u611b\u8036\uff01\uff01\uff01\uff01\uff01", "reply": "", "id": 11717137, "name": "\ud83c\udf6c\u53f2\u8fea\u5947\u6ce1\u6ce1\u5152\ud83c\udf6c"}], "last": [], "noMoreReplies": true}, "images": ["http://filestoresg1.beetalkmobile.com:8081/file/a063a24ef0f11cc2e2e91c7b5c9a7c92"], "id": 18470381}]}
