{"noMoreComments": true, "cursorEnd": 0, "id": "1911063", "comments": [{"postBy": {"location": "\u6843\u5712\u00b7\u53f0\u7063", "utc": 1439576634000, "level": 0, "avatar": "http://filestoresg1.beetalkmobile.com:8081/file/3332560375193835788", "name": "\ud83c\udfa7"}, "content": "\u5805\u6301\u5922\u60f3", "urls": [], "replies": {"first": [{"content": "\u6211\u7b11\u4e86", "reply": "", "id": 11485435, "name": "\u827e\u827e"}], "last": [{"content": "\u795e\u5716\uff01", "reply": "", "id": 11487091, "name": "\u6a5f\u63b0\u6770"}, {"content": "\u8b1d\u8b1d", "reply": "", "id": 11487934, "name": "\u7c89\u7d72"}], "noMoreReplies": true}, "images": ["http://filestoresg1.beetalkmobile.com:8081/file/2a18fe0bef96b57fe50e79d1f1092616"], "id": 18097243}, {"postBy": {"location": "\u5f70\u5316\u7e23\u00b7\u53f0\u7063", "utc": 1439583545000, "level": 0, "avatar": "http://filestoresg1.beetalkmobile.com:8081/file/-9148078567378322173", "name": "\u7121I Love you"}, "content": "\u6709\u5922\u6700\u7f8e \u52a0\u6cb9", "urls": [], "replies": {"first": [{"content": "\u8b1d\u8b1d", "reply": "", "id": 11487935, "name": "\u7c89\u7d72"}], "last": [], "noMoreReplies": true}, "images": [], "id": 18100206}, {"postBy": {"location": "\u53f0\u6e7e\u7701\u00b7\u4e2d\u56fd", "utc": 1439583705000, "level": 0, "avatar": "http://filestoresg1.beetalkmobile.com:8081/file/5730350043744067844", "name": "\u6a5f\u63b0\u6770"}, "content": "\u52a0\u6cb9\uff01<br /><br />\u80fd\u5805\u6301\u5922\u60f3\u7684\u4eba\u5f88\u53b2\u5bb3\uff01", "urls": [], "replies": {"first": [{"content": "\u8b1d\u8b1d", "reply": "", "id": 11487939, "name": "\u7c89\u7d72"}], "last": [{"content": "\u4e0d\u8b1d\u3002", "reply": "\u7c89\u7d72", "id": 11489265, "name": "\u6a5f\u63b0\u6770"}, {"content": "\u55ef\u6069", "reply": "", "id": 11490888, "name": "\u7c89\u7d72"}], "noMoreReplies": true}, "images": [], "id": 18100258}, {"postBy": {"location": "\u53f0\u4e2d\u5e02\u00b7\u53f0\u7063", "utc": 1439621721000, "level": 0, "avatar": "http://filestoresg1.beetalkmobile.com:8081/file/-4031687024618102363", "name": "\u58f9\u67d2\u4f0d"}, "content": "\u5f88\u68d2\u52a0\u6cb9", "urls": [], "replies": {"first": [{"content": "\u8b1d\u8b1d", "reply": "", "id": 11559779, "name": "\u7c89\u7d72"}], "last": [{"content": "\u4e0d\u6703", "reply": "\u7c89\u7d72", "id": 11565531, "name": "\u58f9\u67d2\u4f0d"}, {"content": "\u55ef\u6069", "reply": "", "id": 11565617, "name": "\u7c89\u7d72"}], "noMoreReplies": true}, "images": [], "id": 18126021}, {"postBy": {"location": "", "utc": 1439633531000, "level": 0, "avatar": "http://filestoresg1.beetalkmobile.com:8081/file/2097695564095148573", "name": "\u2764\ufe0fAnn\u2764\ufe0fMiss\u773c\u888b"}, "content": "\u5922\u60f3\u5e38\u5e38\u90fd\u9059\u4e0d\u53ef\u53ca\uff0c\u628a\u5b83\u8a2d\u5b9a\u6210\u76ee\u6a19\u5427", "urls": [], "replies": {"first": [{"content": "\u597d\u7684", "reply": "", "id": 11559785, "name": "\u7c89\u7d72"}], "last": [], "noMoreReplies": true}, "images": [], "id": 18136652}, {"postBy": {"location": "\u53f0\u5317\u5e02\u00b7\u53f0\u7063", "utc": 1453023491000, "level": 0, "avatar": "http://filestoresg1.beetalkmobile.com:8081/file/-3343790766641967679", "name": "\u59f5\u59f5"}, "content": "\u6211\u4e5f\u5f88\u611b\u5531\u6b4c\u5594", "urls": [], "replies": {"first": [], "last": [], "noMoreReplies": true}, "images": [], "id": 29471581}]}
