{"noMoreComments": true, "cursorEnd": 0, "id": "1956860", "comments": [{"postBy": {"location": "\u5c4f\u6771\u7e23\u00b7\u53f0\u7063", "utc": 1440145602000, "level": 0, "avatar": "http://filestoresg1.beetalkmobile.com:8081/file/-6301264847652256848", "name": "\u7a7a\u767d"}, "content": "  ", "urls": [], "replies": {"first": [], "last": [], "noMoreReplies": true}, "images": ["http://filestoresg1.beetalkmobile.com:8081/file/f2ccb88c2ecb9f7d82fac47137891898", "http://filestoresg1.beetalkmobile.com:8081/file/12caa24235f9ef055f2dadae241a973b", "http://filestoresg1.beetalkmobile.com:8081/file/fa573356053fd9b41b0379296ce79571", "http://filestoresg1.beetalkmobile.com:8081/file/21687a9cfe05d642612ee6b7b80c848b", "http://filestoresg1.beetalkmobile.com:8081/file/fbfae0978cc13e1dc77882dc105eb8c8"], "id": 18566599}]}
