{"noMoreComments": true, "cursorEnd": 0, "id": "1117921", "comments": [{"postBy": {"location": "\u6f8e\u6e56\u7e23\u00b7\u53f0\u7063", "utc": 1430008808000, "level": 0, "avatar": "http://filestoresg1.beetalkmobile.com:8081/file/-9209127853666190807", "name": "\u55e8\u55e8\u9019\u88e1\u662f\u98af=)) "}, "content": "\u54c8\u56c9\ud83d\udc4b\ud83d\udc4b", "urls": [], "replies": {"first": [{"content": "\u55e8\u5b89\u5b89", "reply": "", "id": 6280842, "name": "\u2764\u85cd\u51b0\u2764"}], "last": [{"content": "\u597d\u53cb\u5df2\u767c\ud83d\ude01", "reply": "", "id": 6280906, "name": "\u55e8\u55e8\u9019\u88e1\u662f\u98af=)) "}, {"content": "\u5df2\u78ba\u8a8d", "reply": "", "id": 6307849, "name": "\u2764\u85cd\u51b0\u2764"}], "noMoreReplies": true}, "images": [], "id": 9745821}, {"postBy": {"location": "\u6843\u5712\u5e02\u00b7\u53f0\u7063", "utc": 1430023639000, "level": 0, "avatar": "http://filestoresg1.beetalkmobile.com:8081/file/-34841323218576151", "name": "\u9ed1\u6697\u4e16\u754c"}, "content": "\u55e8\u55e8", "urls": [], "replies": {"first": [{"content": "\u55e8 ", "reply": "", "id": 6307852, "name": "\u2764\u85cd\u51b0\u2764"}], "last": [], "noMoreReplies": true}, "images": [], "id": 9761224}, {"postBy": {"location": "Changhua County\u00b7Taiwan", "utc": 1430067238000, "level": 0, "avatar": "http://filestoresg1.beetalkmobile.com:8081/file/1384057548804797930", "name": "\u7267\u53d4(\u5df2\u5a5a\u4eba\u592b)"}, "content": "\u77ed\u9aee\u770b\u8d77\u4f86\u66f4\u5e74\u8f15\u4e86\u2026", "urls": [], "replies": {"first": [{"content": "\u8b1d\u8b1d", "reply": "", "id": 6374229, "name": "\u2764\u85cd\u51b0\u2764"}], "last": [], "noMoreReplies": true}, "images": [], "id": 9817385}, {"postBy": {"location": "\u9ad8\u96c4\u5e02\u00b7\u53f0\u7063", "utc": 1430072429000, "level": 0, "avatar": "http://filestoresg1.beetalkmobile.com:8081/file/5552051044108779277", "name": "\u67cf\u6f84"}, "content": "\u54c8\u560d\uff5e", "urls": [], "replies": {"first": [{"content": "\u55e8 ", "reply": "", "id": 6374240, "name": "\u2764\u85cd\u51b0\u2764"}], "last": [], "noMoreReplies": true}, "images": [], "id": 9822639}]}
