{"noMoreComments": true, "cursorEnd": 0, "id": "1165838", "comments": [{"postBy": {"location": "\u53f0\u4e2d\u5e02\u00b7\u53f0\u7063", "utc": 1430532436000, "level": 0, "avatar": "http://filestoresg1.beetalkmobile.com:8081/file/-5712304844818924195", "name": "\u8278\u66f0\u5341\u8278\u6bcf"}, "content": "\u600e\u9ebc\u4e0d\u8ddf\u6211\u544a\u767d<br />QQ", "urls": [], "replies": {"first": [{"content": "\u56e0\u70ba\u6211\u662f\u6c92\u4eba\u8ddf\u6211\u544a\u767d\u554a\uff01", "reply": "", "id": 6625234, "name": "\u745e\u745e\u264c\ufe0f\ud83d\udc33 R\u20dfE\u20dfL\u20dfA\u20dfX\u20dfI\u20dfN\u20dfG\u20df"}], "last": [], "noMoreReplies": true}, "images": [], "id": 10253519}, {"postBy": {"location": "\u53f0\u5357\u5e02\u00b7\u53f0\u7063", "utc": 1430569593000, "level": 0, "avatar": "http://filestoresg1.beetalkmobile.com:8081/file/-948852143031676416", "name": "\u5c0f\u8c46"}, "content": "\u6211\u4e5f\u597d\u60f3\u5c0d\u5fc3\u5100\u537b\u53c8\u62d2\u7d55\u6211\u7684\u4ed6\u544a\u767d<br />\u53ef\u662f\u6211\u5be6\u5728\u6c92\u6709\u52c7\u6c23\u554a\u54c8\u54c8\u54c8<br /><br />\u6211\u7684\u52c7\u6c23\u6389\u4e86\u5e6b\u6211\u627e\u4e00\u4e0b\u597d\u55ce\ud83d\ude02", "urls": [], "replies": {"first": [{"content": "\uff08\u905e\uff09", "reply": "", "id": 6649537, "name": "\u745e\u745e\u264c\ufe0f\ud83d\udc33 R\u20dfE\u20dfL\u20dfA\u20dfX\u20dfI\u20dfN\u20dfG\u20df"}], "last": [], "noMoreReplies": true}, "images": [], "id": 10290844}, {"postBy": {"location": "\u53f0\u5317\u5e02\u00b7\u53f0\u7063", "utc": 1431222622000, "level": 0, "avatar": "http://filestoresg1.beetalkmobile.com:8081/file/-2610765066267990361", "name": "\u91d1\u5927\u98db"}, "content": "\u6211\u7684\u52c7\u6c23\u52d2?", "urls": [], "replies": {"first": [], "last": [], "noMoreReplies": true}, "images": [], "id": 10889221}]}
