{"noMoreComments": false, "cursorEnd": 21, "id": "1757826", "comments": [{"postBy": {"location": "\u9ad8\u96c4\u5e02\u00b7\u53f0\u7063", "utc": 1437704758000, "level": 0, "avatar": "http://filestoresg1.beetalkmobile.com:8081/file/-5419681928455878145", "name": "\u6bdb\u6bdb"}, "content": "\u81ea\u6211\u4fdd\u8b77\u592a\u5f37\u70c8   \u8a66\u8457\u5f80\u597d\u8655\u60f3\u60f3   \u4e8b\u60c5\u6703\u6bd4\u8f03\u4e0d\u4e00\u6a23", "urls": [], "replies": {"first": [{"content": "\u4e0d\u3002\u3002\u662f\u4eba\u5fc3\u8b8a\u4e86", "reply": "", "id": 10476159, "name": "\u4e0d\u662f\u5929\u4f7f\ud83d\udc7c\u662f\u60e1\u9b54\ud83d\udc7f\u3002\ud83d\udc96\u5c0f\u66fc"}], "last": [{"content": "\u662f\u55ce", "reply": "", "id": 10479499, "name": "\u4e0d\u662f\u5929\u4f7f\ud83d\udc7c\u662f\u60e1\u9b54\ud83d\udc7f\u3002\ud83d\udc96\u5c0f\u66fc"}, {"content": "\u662f\u7684\uff01\uff01\uff01", "reply": "\u4e0d\u662f\u5929\u4f7f\ud83d\udc7c\u662f\u60e1\u9b54\ud83d\udc7f\u3002\ud83d\udc96\u5c0f\u66fc", "id": 10479515, "name": "\u6bdb\u6bdb"}], "noMoreReplies": false}, "images": [], "id": 16465972}, {"postBy": {"location": "\u5609\u7fa9\u5e02\u00b7\u53f0\u7063", "utc": 1437705391000, "level": 0, "avatar": "http://filestoresg1.beetalkmobile.com:8081/file/-909779892378697612", "name": "\u660e"}, "content": "\u5f88\u6f02\u4eae\u5695", "urls": [], "replies": {"first": [], "last": [], "noMoreReplies": true}, "images": [], "id": 16466491}, {"postBy": {"location": "\u5609\u7fa9\u5e02\u00b7\u53f0\u7063", "utc": 1437705391000, "level": 0, "avatar": "http://filestoresg1.beetalkmobile.com:8081/file/-909779892378697612", "name": "\u660e"}, "content": "\u5f88\u6f02\u4eae\u5695", "urls": [], "replies": {"first": [], "last": [], "noMoreReplies": true}, "images": [], "id": 16466493}, {"postBy": {"location": "\u5609\u7fa9\u5e02\u00b7\u53f0\u7063", "utc": 1437705392000, "level": 0, "avatar": "http://filestoresg1.beetalkmobile.com:8081/file/-909779892378697612", "name": "\u660e"}, "content": "\u5f88\u6f02\u4eae\u5695", "urls": [], "replies": {"first": [], "last": [], "noMoreReplies": true}, "images": [], "id": 16466494}, {"postBy": {"location": "\u53f0\u4e2d\u5e02\u00b7\u53f0\u7063", "utc": 1437720840000, "level": 0, "avatar": "http://filestoresg1.beetalkmobile.com:8081/file/2484471868608625097", "name": "Eason"}, "content": "\u611f\u60c5\u5c31\u50cf\u8ced\u535a\uff0c\u904b\u6c23\u6709\u597d\u6709\u58de..\u5c31\u770b\u59b3\u9084\u9858\u4e0d\u9858\u610f\u8ced\u56c9\uff5e", "urls": [], "replies": {"first": [], "last": [], "noMoreReplies": true}, "images": [], "id": 16481593}, {"postBy": {"location": "\u65b0\u5317\u5e02\u00b7\u53f0\u7063", "utc": 1437722228000, "level": 0, "avatar": "http://filestoresg1.beetalkmobile.com:8081/file/-160602353704508184", "name": "\u9673\u5c0f\u5747"}, "content": "\u53ea\u540c\u610f\u4f60\u7b2c\u4e00\u53e5\u3002\u3002\u3002<br /><br />\u4f46\u5f80\u5f80\u50b7\u6700\u6df1\u7684\u5c31\u662f\u90a3\u500b\u4f60\u6700\u91cd\u8981\u6700\u76f8\u4fe1\u7684\u4eba\u3002<br />\u5207\u8eab\u4e4b\u75db\u3002<br /><br />\u81ea\u5df1\u600e\u9ebc\u60f3\u9084\u662f\u6700\u91cd\u8981\u7684\u3002", "urls": [], "replies": {"first": [{"content": "\u6240\u4ee5\u4ee5\u5f8c\u91cd\u8981\u548c\u76f8\u4fe1\n\u53ea\u89815-6\u5206\u5c31\u597d", "reply": "", "id": 10487347, "name": "\u4e0d\u662f\u5929\u4f7f\ud83d\udc7c\u662f\u60e1\u9b54\ud83d\udc7f\u3002\ud83d\udc96\u5c0f\u66fc"}, {"content": "\u9019\u7e3d\u662f\u5f88\u96e3\u8b1b\u8036\u3002\u3002\u3002\u4f46\u662f\u5f80\u5f80\u90fd\u662f\u5fe0\u8a00\u9006\u8033\u554a\u3002\n\u597d\u807d\u8a71\u5f80\u5f80\u90fd\u662f\u6577\u884d\u7684\u5ba2\u5957\u8a71\u3002", "reply": "\u4e0d\u662f\u5929\u4f7f\ud83d\udc7c\u662f\u60e1\u9b54\ud83d\udc7f\u3002\ud83d\udc96\u5c0f\u66fc", "id": 10668107, "name": "\u9673\u5c0f\u5747"}], "last": [], "noMoreReplies": true}, "images": [], "id": 16482967}, {"postBy": {"location": "", "utc": 1437722674000, "level": 0, "avatar": "http://filestoresg1.beetalkmobile.com:8081/file/-8541384552571774134", "name": "Sun"}, "content": "\u4f46\u662f  \u6211\u4ecd\u6703\u76f8\u4fe1\u59b3\u2026\u2026", "urls": [], "replies": {"first": [{"content": "\u8b1d\u8b1d", "reply": "", "id": 10487304, "name": "\u4e0d\u662f\u5929\u4f7f\ud83d\udc7c\u662f\u60e1\u9b54\ud83d\udc7f\u3002\ud83d\udc96\u5c0f\u66fc"}], "last": [], "noMoreReplies": true}, "images": [], "id": 16483426}, {"postBy": {"location": "\u53f0\u5317\u5e02\u00b7\u53f0\u7063", "utc": 1437722754000, "level": 0, "avatar": "http://filestoresg1.beetalkmobile.com:8081/file/-361102703350926507", "name": "lewis"}, "content": "\u59b3\u7684\u5fc3\u662f\u73bb\u7483\u505a\u7684\u55ce \u90a3\u9ebc\u5bb9\u6613\u53d7\u50b7", "urls": [], "replies": {"first": [{"content": "\u5979\u5df2\u7d93\u8b8a\u9435\u4e86", "reply": "", "id": 10487319, "name": "\u4e0d\u662f\u5929\u4f7f\ud83d\udc7c\u662f\u60e1\u9b54\ud83d\udc7f\u3002\ud83d\udc96\u5c0f\u66fc"}], "last": [{"content": "\u6709\u9053\u7406  \u53ef\u4ee5\u56de\u8840\uff01\uff01", "reply": "\u4e0d\u662f\u5929\u4f7f\ud83d\udc7c\u662f\u60e1\u9b54\ud83d\udc7f\u3002\ud83d\udc96\u5c0f\u66fc", "id": 10487676, "name": "lewis"}, {"content": "\ud83d\ude02\ud83d\ude02\ud83d\ude02\ud83d\ude02\ud83d\ude02\ud83d\ude02\ud83d\ude02", "reply": "", "id": 10487748, "name": "\u4e0d\u662f\u5929\u4f7f\ud83d\udc7c\u662f\u60e1\u9b54\ud83d\udc7f\u3002\ud83d\udc96\u5c0f\u66fc"}], "noMoreReplies": false}, "images": [], "id": 16483523}, {"postBy": {"location": "\u96f2\u6797\u7e23\u00b7\u53f0\u7063", "utc": 1437723044000, "level": 0, "avatar": "http://filestoresg1.beetalkmobile.com:8081/file/-4181230506060960359", "name": "Wang Song"}, "content": "\u55ef\u2026\u90a3\u59b3\u5b64\u7368\u7d42\u8001\u5427\uff0c\u52a0\u6cb9", "urls": [], "replies": {"first": [{"content": "\u8b1d\u8b1d\u4f60\u5594\uff01\u4f60\u81ea\u5df1\u4e5f\u52a0\u6cb9\u3002\u800c\u4e14\u6211\u6703\u4e0d\u6703\u5b64\u8001\u7d42\u8eab\u4f60\u8aaa\u7684\u6e96\u55ce", "reply": "", "id": 10486828, "name": "\u4e0d\u662f\u5929\u4f7f\ud83d\udc7c\u662f\u60e1\u9b54\ud83d\udc7f\u3002\ud83d\udc96\u5c0f\u66fc"}], "last": [{"content": "\u8ca0\u8ca0\u4e0d\u6703\u5f97\u6b63\n\u6703\u3002\u3002\u3002\u3002\u3002\u66f4\u5b8c\u86cb", "reply": "", "id": 10489433, "name": "\u4e0d\u662f\u5929\u4f7f\ud83d\udc7c\u662f\u60e1\u9b54\ud83d\udc7f\u3002\ud83d\udc96\u5c0f\u66fc"}, {"content": "\ud83d\ude28\ud83d\ude28\ud83d\ude28", "reply": "", "id": 10489515, "name": "Wang Song"}], "noMoreReplies": false}, "images": [], "id": 16483872}, {"postBy": {"location": "\u53f0\u4e2d\u5e02\u00b7\u53f0\u7063", "utc": 1437723739000, "level": 0, "avatar": "http://filestoresg1.beetalkmobile.com:8081/file/7364102282283541132", "name": "\u4e00\u8d77\u7761"}, "content": "\u59b3\u5bb6\u4eba\u871c\u95a8\u597d\u670b\u53cb\u5168\u90fd\u662f\u964c\u751f\u4eba\uff1f", "urls": [], "replies": {"first": [{"content": "\u5c31\u7b97\u662f\u5bb6\u4eba\u3002\u95a8\u871c\u3002\u670b\u53cb\n\u6709\u6642\u4e5f\u6703\u50cf\u964c\u751f\u4eba\n\u5225\u5426\u8a8d", "reply": "", "id": 10487283, "name": "\u4e0d\u662f\u5929\u4f7f\ud83d\udc7c\u662f\u60e1\u9b54\ud83d\udc7f\u3002\ud83d\udc96\u5c0f\u66fc"}], "last": [], "noMoreReplies": true}, "images": [], "id": 16484564}, {"postBy": {"location": "\u9ad8\u96c4\u5e02\u00b7\u53f0\u7063", "utc": 1437724146000, "level": 0, "avatar": "http://filestoresg1.beetalkmobile.com:8081/file/-8712935845562606911", "name": "\u901a\u8a71\u4e2d"}, "content": "\u5e79\u561b\u9019\u6a23<br />\u518d\u6b21\u5b78\u7fd2\u5982\u4f55\u770b\u4eba\u5982\u4f55\u9632\u885b,,,\u53ef\u4ee5\u4ea4\u65b0\u670b\u53cb\u53c8\u4e0d\u50b7\u4eba\u50b7\u5df1\u4e0d\u662f\u66f4\u597d", "urls": [], "replies": {"first": [{"content": "\u5f88\u6b63\u9762\u8036\uff01\n\u4f46\u6211\u4e0d\u6b63\u9762", "reply": "", "id": 10487431, "name": "\u4e0d\u662f\u5929\u4f7f\ud83d\udc7c\u662f\u60e1\u9b54\ud83d\udc7f\u3002\ud83d\udc96\u5c0f\u66fc"}], "last": [{"content": "\u6211\u77e5,,,,\u59b3\u90fd\u5074\u9762", "reply": "\u4e0d\u662f\u5929\u4f7f\ud83d\udc7c\u662f\u60e1\u9b54\ud83d\udc7f\u3002\ud83d\udc96\u5c0f\u66fc", "id": 10487531, "name": "\u901a\u8a71\u4e2d"}, {"content": "\ud83d\ude02\ud83d\ude02\ud83d\ude02\ud83d\ude02\ud83d\ude02\ud83d\ude02\ud83d\ude02", "reply": "", "id": 10487582, "name": "\u4e0d\u662f\u5929\u4f7f\ud83d\udc7c\u662f\u60e1\u9b54\ud83d\udc7f\u3002\ud83d\udc96\u5c0f\u66fc"}], "noMoreReplies": true}, "images": [], "id": 16484975}, {"postBy": {"location": "\u53f0\u5357\u5e02\u00b7\u53f0\u7063", "utc": 1437725674000, "level": 0, "avatar": "http://filestoresg1.beetalkmobile.com:8081/file/-1851219139532506818", "name": "\u97d3\u68ee\u5bf6\u4e00"}, "content": "\u6240\u4ee5\u5c0d\u4eba\u9700\u8981\u6709\u9ede\u6212\u5fc3\u5728", "urls": [], "replies": {"first": [{"content": "\u4f60\u8aaa\u5c0d\u4e86", "reply": "", "id": 10489446, "name": "\u4e0d\u662f\u5929\u4f7f\ud83d\udc7c\u662f\u60e1\u9b54\ud83d\udc7f\u3002\ud83d\udc96\u5c0f\u66fc"}], "last": [], "noMoreReplies": true}, "images": [], "id": 16486483}, {"postBy": {"location": "\u53f0\u5357\u5e02\u00b7\u53f0\u7063", "utc": 1437725967000, "level": 0, "avatar": "http://filestoresg1.beetalkmobile.com:8081/file/-4121213663278461439", "name": "\u5c0f\u5112\u270c"}, "content": "\u9019\u6a23\u4e0d\u597d\u5427\uff01<br />", "urls": [], "replies": {"first": [{"content": "\u51fa\u606f\u5f9e\u4f86\u4e0d\u662f\u7559\u7d66\u76f8\u4fe1\u5225\u4eba\u9019\u4ef6\u4e8b\u4e0a\u3002\u3002\u3002", "reply": "", "id": 10489479, "name": "\u4e0d\u662f\u5929\u4f7f\ud83d\udc7c\u662f\u60e1\u9b54\ud83d\udc7f\u3002\ud83d\udc96\u5c0f\u66fc"}], "last": [{"content": "\u6211\u7684\u610f\u601d\u662f\u4e0d\u8981\u56e0\u70ba\u4e00\u4e9b\u632b\u6298\u800c\u8b8a\u6210\u9019\u6a23\u5427\uff01\u89ba\u5f97\u5c31\u7576\u4f5c\u4e00\u7a2e\u7d93\u9a57\uff0c\u4f55\u6cc1\u5bb6\u4eba\u662f\u6700\u89aa\u7684\u4eba\uff0c\u5225\u9023\u5bb6\u4eba\u90fd\u7576\u4f5c\u964c\u751f\u4eba\u5427\uff01", "reply": "", "id": 10489685, "name": "\u5c0f\u5112\u270c"}, {"content": "\ud83d\ude00\ud83d\ude00\ud83d\ude00\ud83d\ude00\ud83d\ude00\ud83d\ude00", "reply": "", "id": 10496938, "name": "\u4e0d\u662f\u5929\u4f7f\ud83d\udc7c\u662f\u60e1\u9b54\ud83d\udc7f\u3002\ud83d\udc96\u5c0f\u66fc"}], "noMoreReplies": true}, "images": ["http://filestoresg1.beetalkmobile.com:8081/file/8a5a1f79d20b315b7ce8d85ac0b7e246"], "id": 16486758}, {"postBy": {"location": "", "utc": 1437727195000, "level": 0, "avatar": "http://filestoresg1.beetalkmobile.com:8081/file/5410249223435752200", "name": "\u8001\u53f8\u6a5f\u5e36\u5e36\u6211"}, "content": "\u9019\u5c31\u662f\u4eba\u8518", "urls": [], "replies": {"first": [{"content": "\u4eba\u5c31\u662f\u4f86\u6298\u78e8\u7684", "reply": "", "id": 10489499, "name": "\u4e0d\u662f\u5929\u4f7f\ud83d\udc7c\u662f\u60e1\u9b54\ud83d\udc7f\u3002\ud83d\udc96\u5c0f\u66fc"}, {"content": "\u591a\u591a\u5c11\u5c11\u4e5f\u8981\u6413\u4e00\u4e0b", "reply": "", "id": 10553834, "name": "\u8001\u53f8\u6a5f\u5e36\u5e36\u6211"}], "last": [], "noMoreReplies": true}, "images": [], "id": 16487993}, {"postBy": {"location": "\u9ad8\u96c4\u5e02\u00b7\u53f0\u7063", "utc": 1437730605000, "level": 0, "avatar": "http://filestoresg1.beetalkmobile.com:8081/file/498795650137668096", "name": "\u675c\u675c\u5148\u751f\ud83c\udfa9"}, "content": "\u8aaa\u7684\u5f88\u597d...<br /><br />\u8d8a\u719f\u6089\u7684\u6539\u8b8a\u8d8a\u964c\u751f", "urls": [], "replies": {"first": [{"content": "\u771f\u7684", "reply": "", "id": 10496946, "name": "\u4e0d\u662f\u5929\u4f7f\ud83d\udc7c\u662f\u60e1\u9b54\ud83d\udc7f\u3002\ud83d\udc96\u5c0f\u66fc"}], "last": [{"content": "\u6240\u4ee5\u59b3\u525b\u544a\u5225\u4e00\u6bb5\u6200\u611b\u56c9\uff1f", "reply": "", "id": 10500392, "name": "\u675c\u675c\u5148\u751f\ud83c\udfa9"}, {"content": "\u5657\u3002\u6211\u544a\u5225\u4e86\u81ea\u5df1\u7684\u8a18\u61b6", "reply": "", "id": 10502920, "name": "\u4e0d\u662f\u5929\u4f7f\ud83d\udc7c\u662f\u60e1\u9b54\ud83d\udc7f\u3002\ud83d\udc96\u5c0f\u66fc"}], "noMoreReplies": true}, "images": [], "id": 16491403}, {"postBy": {"location": "\u53f0\u4e2d\u5e02\u00b7\u53f0\u7063", "utc": 1437732727000, "level": 0, "avatar": "http://filestoresg1.beetalkmobile.com:8081/file/-2025591777127922594", "name": "\u5f6d\u54e5"}, "content": "\u4eba\u5230\u4e00\u500b\u968e\u6bb5\u5c31\u5bb9\u6613\u7522\u751f\u81ea\u6211\u4fdd\u8b77\u6a5f\u5236<br />\u6709\u4eba\u4fdd\u8b77\u904e\u982d\uff0c\u5247\u50b7\u5bb3\u5230\u4e86\u5225\u4eba<br />\u6162\u6162\u7684\u91cd\u62fe\u4fe1\u5fc3\u5427<br />\u9019\u4e16\u754c\u9084\u662f\u5145\u6eff\u8457\u90a3\u4e00\u9ede\u5e0c\u671b", "urls": [], "replies": {"first": [{"content": "\u5e0c\u671b\u9019\u4e16\u754c\u9084\u662f\u7f8e\u9e97\u7684", "reply": "", "id": 10496972, "name": "\u4e0d\u662f\u5929\u4f7f\ud83d\udc7c\u662f\u60e1\u9b54\ud83d\udc7f\u3002\ud83d\udc96\u5c0f\u66fc"}], "last": [], "noMoreReplies": true}, "images": [], "id": 16493556}, {"postBy": {"location": "\u5c4f\u6771\u7e23\u00b7\u53f0\u7063", "utc": 1437736840000, "level": 0, "avatar": "http://filestoresg1.beetalkmobile.com:8081/file/536772793398631995", "name": "."}, "content": "\u592a\u611b\u4e00\u500b\u4eba\u5c31\u6703\u5931\u53bb\u88ab\u611b\u7684\u6b0a\u5229<br />\u8d8a\u611b\u5c31\u8d8a\u4e0d\u88ab\u73cd\u60dc", "urls": [], "replies": {"first": [{"content": "\u6216\u8a31", "reply": "", "id": 10496986, "name": "\u4e0d\u662f\u5929\u4f7f\ud83d\udc7c\u662f\u60e1\u9b54\ud83d\udc7f\u3002\ud83d\udc96\u5c0f\u66fc"}], "last": [], "noMoreReplies": true}, "images": [], "id": 16497653}, {"postBy": {"location": "\u5b9c\u862d\u7e23\u00b7\u53f0\u7063", "utc": 1437736965000, "level": 0, "avatar": "http://filestoresg1.beetalkmobile.com:8081/file/8092268148066904580", "name": "\u96c4\u5927\u53d4\ud83d\udc3b\ud83d\udc3c\ud83d\udc28"}, "content": "\u4fe1\u4efb<br />\u662f\u9700\u8981\u6642\u9593<br />\u6162\u6162\u5efa\u7acb\u4e86\uff01", "urls": [], "replies": {"first": [{"content": "\u525b\u597d\u6642\u9593\u4e5f\u662f\u6467\u6bc0\u4fe1\u4efb\u7684\u57fa\u790e", "reply": "", "id": 10497011, "name": "\u4e0d\u662f\u5929\u4f7f\ud83d\udc7c\u662f\u60e1\u9b54\ud83d\udc7f\u3002\ud83d\udc96\u5c0f\u66fc"}, {"content": "\u6240\u4ee5\u6642\u9593\uff0c\u624d\u53ef\u770b\u4eba\u5fc3!", "reply": "\u4e0d\u662f\u5929\u4f7f\ud83d\udc7c\u662f\u60e1\u9b54\ud83d\udc7f\u3002\ud83d\udc96\u5c0f\u66fc", "id": 10497159, "name": "\u96c4\u5927\u53d4\ud83d\udc3b\ud83d\udc3c\ud83d\udc28"}], "last": [], "noMoreReplies": true}, "images": [], "id": 16497792}, {"postBy": {"location": "\u6843\u5712\u5e02\u00b7\u53f0\u7063", "utc": 1437737256000, "level": 0, "avatar": "http://filestoresg1.beetalkmobile.com:8081/file/-1340981971571735806", "name": "\u751f\u7121\u53ef\u6200"}, "content": "\u96d6\u7136\u76f8\u4fe1\u4eba\u5f88\u5bb9\u6613\u53d7\u50b7\uff0c\u8207\u5176\u4e0d\u76f8\u4fe1\u4eba\u6211\u5be7\u9858\u76f8\u4fe1\u4eba\uff0c\u56e0\u70ba\u6211\u89ba\u5f97\u4e26\u4e0d\u662f\u6240\u6709\u4eba\u90fd\u4e0d\u53ef\u4fe1\uff0c\u6240\u4ee5\u6211\u9084\u662f\u9078\u64c7\u76f8\u4fe1\uff0c\u4e5f\u8a31\u6211\u6bd4\u8f03\u50bb\u5427\u3002", "urls": [], "replies": {"first": [{"content": "\u662f\u554a\uff01\u6bcf\u500b\u4eba\u7d93\u6b77\u4e0d\u540c", "reply": "", "id": 10497028, "name": "\u4e0d\u662f\u5929\u4f7f\ud83d\udc7c\u662f\u60e1\u9b54\ud83d\udc7f\u3002\ud83d\udc96\u5c0f\u66fc"}, {"content": "\u59b3\u8aaa\u7684\u6c92\u932f\uff0c\u6216\u8a31\u662f\u6bcf\u500b\u4eba\u7d93\u6b77\u4e0d\u540c\u5427\uff0c\u53ef\u662f\u6211\u627f\u8a8d\u6211\u662f\u500b\u6bd4\u8f03\u7b28\u7684\u4eba\u3002", "reply": "\u4e0d\u662f\u5929\u4f7f\ud83d\udc7c\u662f\u60e1\u9b54\ud83d\udc7f\u3002\ud83d\udc96\u5c0f\u66fc", "id": 10498919, "name": "\u751f\u7121\u53ef\u6200"}], "last": [], "noMoreReplies": true}, "images": [], "id": 16498096}]}
