{"noMoreComments": true, "cursorEnd": 0, "id": "1776101", "comments": [{"postBy": {"location": "\u53f0\u5357\u5e02\u00b7\u53f0\u7063", "utc": 1437924148000, "level": 0, "avatar": "http://filestoresg1.beetalkmobile.com:8081/file/5661013740151251075", "name": "\u570b\u969b\u6d41\u6d6a\u6f22"}, "content": "\u7b49\u6211\u5e74\u6536\u5165\u591a\u3127\u500b\u96f6\u61c9\u8a72\u5c31\u6709\u90a3\u5fc3\u81df\u6253<br />3000/1000<br />10000/5000", "urls": [], "replies": {"first": [], "last": [], "noMoreReplies": true}, "images": [], "id": 16666579}, {"postBy": {"location": "Pingtung County\u00b7Taiwan", "utc": 1437924323000, "level": 0, "avatar": "http://filestoresg1.beetalkmobile.com:8081/file/-8431938068214444795", "name": "\u963f\u5e03"}, "content": "\u65bd\u4e3b\u2026\u73fe\u5be6\u662f\u6b98\u9177\u7684", "urls": [], "replies": {"first": [], "last": [], "noMoreReplies": true}, "images": [], "id": 16666851}]}
