{"noMoreComments": true, "cursorEnd": 0, "id": "1750826", "comments": [{"postBy": {"location": "\u53f0\u5357\u5e02\u00b7\u53f0\u7063", "utc": 1437627733000, "level": 0, "avatar": "http://filestoresg1.beetalkmobile.com:8081/file/-6816370658424010602", "name": "\u963f\u52f3"}, "content": "\u53ef\u611b", "urls": [], "replies": {"first": [{"content": "\u9084\u597d", "reply": "", "id": 10439113, "name": "\u5225\u628a\u8cb7\u96de\u6392\u7684\u9322 \u62ff\u53bb\u5ad6\u5993"}], "last": [], "noMoreReplies": true}, "images": [], "id": 16396131}, {"postBy": {"location": "\u5609\u7fa9\u5e02\u00b7\u53f0\u7063", "utc": 1437633895000, "level": 0, "avatar": "http://filestoresg1.beetalkmobile.com:8081/file/2241323668223745067", "name": "\u54e6"}, "content": "\u9ad8\u4e09\u8def\u904e\uff0c\u6b61\u8fce\u804a\u54e6", "urls": [], "replies": {"first": [{"content": "\u55e8\u55e8", "reply": "", "id": 10439108, "name": "\u5225\u628a\u8cb7\u96de\u6392\u7684\u9322 \u62ff\u53bb\u5ad6\u5993"}], "last": [], "noMoreReplies": true}, "images": [], "id": 16402346}]}
