{"noMoreComments": true, "cursorEnd": 0, "id": "1798248", "comments": [{"postBy": {"location": "\u53f0\u5357\u5e02\u00b7\u53f0\u7063", "utc": 1438197039000, "level": 0, "avatar": "http://filestoresg1.beetalkmobile.com:8081/file/-2202091989623418089", "name": "Swan\u2728"}, "content": "\u60f3\u5ff5\u5230\u4e0d\u884c \u5c31\u8cb7\u8eca\u7968\u4e86", "urls": [], "replies": {"first": [{"content": "\u5979\u7684\u5bb6\u7ba1\u56b4 \u4e0d\u80fd\u88ab\u767c\u73fe\u4ea4\u7537\u53cb\n\u6211\u662f\u5361\u5230\u4e0a\u8ab2 \u4e0a\u73ed \u4f11\u606f\u6642\u9593\u975e\u5e38\u5c11 \u9023\u5047\u5f88\u96e3>_<", "reply": "", "id": 10753385, "name": "cc"}], "last": [], "noMoreReplies": true}, "images": [], "id": 16905960}, {"postBy": {"location": "\u9ad8\u96c4\u5e02\u00b7\u53f0\u7063", "utc": 1438198384000, "level": 0, "avatar": "http://filestoresg1.beetalkmobile.com:8081/file/8195135154097844227", "name": "\u55c4\u55c4"}, "content": "\u611b\u60c5\u9019\u6771\u897f\u9700\u8981\u6162\u6162\u57f9\u990a<br />\u5225\u6025\u8457\u5347\u6eab \u53cd\u800c\u6703\u71d9\u50b7\u81ea\u5df1\u6216\u5979<br /><br />\u4f60\u5011\u5728\u4e00\u8d77\u5169\u5e74\u4e86 \u4e00\u5b9a\u90fd\u5f88\u73cd\u60dc\u624d\u6703\u7dad\u6301\u9019\u9ebc\u4e45<br />\u4e00\u6b65\u4e00\u6b65\u4f86 \u6642\u9593\u5dee\u4e0d\u591a \u5c31\u6d6e\u51fa\u5730\u9762\u898b\u7236\u6bcd<br />\u8b93\u4ed6\u5011\u8a8d\u53ef\u4f60<br /><br />\u9664\u975e\u5973\u65b9\u5e74\u7d00\u9084\u592a\u5c0f", "urls": [], "replies": {"first": [{"content": "\u7236\u6bcd\u898b\u904e \u53ea\u662f\u4e0d\u80fd\u5e38\u898b\u9762\u7e3d\u89ba\u5f97\u5c11\u4e86\u4ec0\u9ebc", "reply": "", "id": 10754507, "name": "cc"}, {"content": "\u53ef\u80fd\u4e00\u7a2e\u966a\u4f34\u7684\u611f\u89ba\u800c\u5df2", "reply": "cc", "id": 10755782, "name": "\u55c4\u55c4"}], "last": [], "noMoreReplies": true}, "images": [], "id": 16906522}, {"postBy": {"location": "\u6843\u5712\u5e02\u00b7\u53f0\u7063", "utc": 1438203237000, "level": 0, "avatar": "http://filestoresg1.beetalkmobile.com:8081/file/-6328901702506983657", "name": "\u838a\u4e01\u4e01"}, "content": "\u54c7\u8cfd\uff0c\u5169\u5e7410\u6b21\uff0c\u600e\u7e7c\u7e8c\u5440", "urls": [], "replies": {"first": [{"content": "\u4e00\u500b\u611b\u5b57\u8b93\u6211\u6490\u8457", "reply": "", "id": 10754510, "name": "cc"}, {"content": "\u60c5\u8da3\u9ede\uff0c\u4f86\u8996\u8a0a\u5c0d\u8a71\n\u5e73\u5747\u5169\u500b\u6708\u591a\u624d\u898b\u4e00\u6b21\u8036\uff01\n\u6709\u672a\u4f86\u561b\uff1f", "reply": "", "id": 10758893, "name": "\u838a\u4e01\u4e01"}], "last": [], "noMoreReplies": true}, "images": [], "id": 16908037}, {"postBy": {"location": "\u9ad8\u96c4\u5e02\u00b7\u53f0\u7063", "utc": 1438203776000, "level": 0, "avatar": "http://filestoresg1.beetalkmobile.com:8081/file/-4481661070745378231", "name": "7\u742a\u270c"}, "content": "\u6490\u4e45\u5c31\u7d2f\u4e86\u554a\uff0c<br />\u4e0d\u904e\u4f60\u9019\u6a23\u7b97\u9084\u597d<br />\u81f3\u5c11\u4f60\u9084\u6709\u5fc3\u8981\u806f\u7d61\u4e0d\u662f\u55ce<br />\u6709\u4e9b\u4eba\u3002\u9023\u806f\u7d61\u90fd\u61f6\u4e86\u3002", "urls": [], "replies": {"first": [{"content": "\u4e0d\u958b\u5fc3\u4e5f\u53ef\u4ee5\u8aaa\u8aaa\u770b \u61c9\u8a72\u59b3\u8ddf\u59b3\u7684\u7537\u5b69\u6e9d\u901a\u51fa\u4e86\u554f\u984c ", "reply": "", "id": 10754685, "name": "cc"}, {"content": "\u6e9d\u901a\u5728\u591a\u9084\u662f\u4e00\u6a23.", "reply": "", "id": 10754979, "name": "7\u742a\u270c"}], "last": [], "noMoreReplies": true}, "images": [], "id": 16908187}]}
