{"noMoreComments": true, "cursorEnd": 0, "id": "1025756", "comments": [{"postBy": {"location": "\u5f70\u5316\u7e23\u00b7\u53f0\u7063", "utc": 1429177011000, "level": 0, "avatar": "http://filestoresg1.beetalkmobile.com:8081/file/-6298825035137183420", "name": "\u975c\u5100\u02ca\u2022_\u2022\u02cb"}, "content": "\u8a8d\u8b58\u6211\u5c31\u597d\u4e86\u554a", "urls": [], "replies": {"first": [], "last": [], "noMoreReplies": true}, "images": [], "id": 8938304}, {"postBy": {"location": "\u5f70\u5316\u7e23\u00b7\u53f0\u7063", "utc": 1429188573000, "level": 0, "avatar": "http://filestoresg1.beetalkmobile.com:8081/file/985173414787999488", "name": "\u5b87\u5b99"}, "content": "\u54c8\u54c8\u54c8\u4f60\u53c8\u4e0d\u7d66\u6211\u771f\u6b63\u8a8d\u8b58", "urls": [], "replies": {"first": [], "last": [], "noMoreReplies": true}, "images": [], "id": 8950260}, {"postBy": {"location": "\u53f0\u4e2d\u5e02\u00b7\u53f0\u7063", "utc": 1429189998000, "level": 0, "avatar": "http://filestoresg1.beetalkmobile.com:8081/file/-6298825035137183420", "name": "\u975c\u5100\u02ca\u2022_\u2022\u02cb"}, "content": "\u6709\u6211\u4e86\u554a \u53ef\u60e1 \u9084\u60f3\u628a\u5176\u4ed6\u54a9\u311b", "urls": [], "replies": {"first": [], "last": [], "noMoreReplies": true}, "images": [], "id": 8952006}, {"postBy": {"location": "\u5f70\u5316\u7e23\u00b7\u53f0\u7063", "utc": 1429199540000, "level": 0, "avatar": "http://filestoresg1.beetalkmobile.com:8081/file/985173414787999488", "name": "\u5b87\u5b99"}, "content": "\u90a3\u5c4b", "urls": [], "replies": {"first": [], "last": [], "noMoreReplies": true}, "images": [], "id": 8965957}, {"postBy": {"location": "\u5f70\u5316\u7e23\u00b7\u53f0\u7063", "utc": 1429239131000, "level": 0, "avatar": "http://filestoresg1.beetalkmobile.com:8081/file/3391150049877005063", "name": "\ud83c\udf39"}, "content": "\u70ba\u4ec0\u9ebc\u8981\u628a\u7dad\u5c3c\u84cb\u4f4f\u81c9", "urls": [], "replies": {"first": [], "last": [], "noMoreReplies": true}, "images": [], "id": 8992097}, {"postBy": {"location": "\u5f70\u5316\u7e23\u00b7\u53f0\u7063", "utc": 1429246554000, "level": 0, "avatar": "http://filestoresg1.beetalkmobile.com:8081/file/985173414787999488", "name": "\u5b87\u5b99"}, "content": "\u54c8\u54c8\u54c8\u56e0\u70ba\u6211\u5728\u63db\u8863\u670d\u6015\u4ed6\u5077\u770b\u54c8\u54c8", "urls": [], "replies": {"first": [], "last": [], "noMoreReplies": true}, "images": [], "id": 8999936}, {"postBy": {"location": "\u5609\u7fa9\u7e23\u00b7\u53f0\u7063", "utc": 1429259296000, "level": 0, "avatar": "http://filestoresg1.beetalkmobile.com:8081/file/2352835038226700403", "name": "\u53ef\u6a02\u679c\u7684\u6a02\u2764"}, "content": "\u6211\u6211\u6211\uff08\u8209\u624b\uff09", "urls": [], "replies": {"first": [], "last": [], "noMoreReplies": true}, "images": [], "id": 9012865}]}
