{"noMoreComments": true, "cursorEnd": 0, "id": "1306580", "comments": [{"postBy": {"location": "\u65b0\u5317\u5e02\u00b7\u53f0\u7063", "utc": 1432146952000, "level": 0, "avatar": "http://filestoresg1.beetalkmobile.com:8081/file/5313573563869736704", "name": "Jerry"}, "content": "\u8a71\u8aaa\u59b3\u5011\u7d14\u4ea4\u53cb\u90fd\u804a\u4ec0\u9ebc\uff1f", "urls": [], "replies": {"first": [{"content": "\u96a8\u4fbf\u804a\u554a\uff0c\u53ea\u662f\u4ea4\u670b\u53cb\uff0c\u4e0d\u662f\u627e\u611b\u4eba\u6216\u70ae\u53cb\uff0c\u61c9\u8a72\u4e0d\u96e3\u7406\u89e3\u624d\u662f..", "reply": "", "id": 7533195, "name": "\u96ef\u96ef\u3126"}, {"content": "\u662f\u4e0d\u96e3\uff0c\u53ea\u662f\u597d\u5947\u5e74\u8f15\u5c0f\u670b\u53cb\u90fd\u804a\u4ec0\u9ebc", "reply": "\u96ef\u96ef\u3126", "id": 7533232, "name": "Jerry"}], "last": [], "noMoreReplies": true}, "images": [], "id": 11694062}, {"postBy": {"location": "", "utc": 1432146995000, "level": 0, "avatar": "http://filestoresg1.beetalkmobile.com:8081/file/5186168750523686231", "name": "\u9038"}, "content": "\u9084\u6c92\u7761\u554a", "urls": [], "replies": {"first": [], "last": [], "noMoreReplies": true}, "images": [], "id": 11694096}, {"postBy": {"location": "Taoyuan City\u00b7Taiwan", "utc": 1432148169000, "level": 0, "avatar": "http://filestoresg1.beetalkmobile.com:8081/file/8732466488481007942", "name": "\ud83d\udc3e\u6c6a\u6c6a\ud83d\udc36\ud83d\udc3e"}, "content": "\u65e9\u9ede\u7761\u6bd4\u8f03\u5be6\u5728", "urls": [], "replies": {"first": [], "last": [], "noMoreReplies": true}, "images": [], "id": 11694637}, {"postBy": {"location": "\u53f0\u4e2d\u5e02\u00b7\u53f0\u7063", "utc": 1432811009000, "level": 0, "avatar": "http://filestoresg1.beetalkmobile.com:8081/file/-4431761934269187606", "name": "\u98db\u7fd4"}, "content": "\u4ea4\u670b\u53cb+1", "urls": [], "replies": {"first": [], "last": [], "noMoreReplies": true}, "images": [], "id": 12226032}]}
