{"noMoreComments": true, "cursorEnd": 0, "id": "1508642", "comments": [{"postBy": {"location": "", "utc": 1434632573000, "level": 0, "avatar": "http://filestoresg1.beetalkmobile.com:8081/file/-6292763421537878694", "name": "\u5a1c\u5a1c\ud83d\udc8b"}, "content": "\u606d\u559c\u4f60", "urls": [], "replies": {"first": [{"content": "\u54ea\u88e1\u68d2\u554a\uff01?", "reply": "", "id": 8822064, "name": "J J "}], "last": [{"content": "\u820a\u7684\u4e0d\u53bb\u65b0\u7684\u4e0d\u4f86", "reply": "J J ", "id": 8822109, "name": "\u5a1c\u5a1c\ud83d\udc8b"}, {"content": "\u662f\u539a\u2026\u59b3\u53c8\u6539\u56deid", "reply": "\u5a1c\u5a1c\ud83d\udc8b", "id": 8822517, "name": "J J "}], "noMoreReplies": true}, "images": ["http://filestoresg1.beetalkmobile.com:8081/file/da7b6bdb18fcaba0e1013dd56b7eb2ef"], "id": 13751510}, {"postBy": {"location": "\u65b0\u5317\u5e02\u00b7\u53f0\u7063", "utc": 1434633431000, "level": 0, "avatar": "http://filestoresg1.beetalkmobile.com:8081/file/-1960511691864204768", "name": "Beetalk\u4f7f\u7528\u8005"}, "content": "\u606d\u559c\u8001\u723a \u8cc0\u559c\u8001\u723a", "urls": [], "replies": {"first": [{"content": "\u606d\u559c\u592b\u4eba \u8cc0\u559c\u592b\u4eba", "reply": "", "id": 8822197, "name": "J J "}], "last": [], "noMoreReplies": true}, "images": [], "id": 13752451}, {"postBy": {"location": "", "utc": 1434633764000, "level": 0, "avatar": "http://filestoresg1.beetalkmobile.com:8081/file/-804878791682547621", "name": "\u9b5a"}, "content": "\u54c8\u54c8\uff0c\u6253\u7d66\u6a5f\u8eca\u884c\u5354\u52a9", "urls": [], "replies": {"first": [{"content": "\u8d70\u56de\u5bb6\u62ff\u9470\u5319", "reply": "", "id": 8822476, "name": "J J "}, {"content": "\n\u54c8\u54c8\uff0c\u5c0f\u5fc3", "reply": "J J ", "id": 8829315, "name": "\u9b5a"}], "last": [], "noMoreReplies": true}, "images": ["http://filestoresg1.beetalkmobile.com:8081/file/c784ad0df2c804117dd315dcd972cd68"], "id": 13752831}, {"postBy": {"location": "\u53f0\u4e2d\u5e02\u00b7\u53f0\u7063", "utc": 1434634245000, "level": 0, "avatar": "http://filestoresg1.beetalkmobile.com:8081/file/-2023199242124468431", "name": "\u767d\u6ce1\u6ce1"}, "content": "\u606d\u559c\u2026\u2026\u4e00\u65e5\u904a\u6c11\uff01", "urls": [], "replies": {"first": [{"content": "\u5657\u2026\u4e0b\u73ed\u624d\u767c\u73fe(\u256f\u0437\u2570)", "reply": "", "id": 8822496, "name": "J J "}], "last": [], "noMoreReplies": true}, "images": [], "id": 13753411}, {"postBy": {"location": "\u53f0\u5357\u5e02\u00b7\u53f0\u7063", "utc": 1434649234000, "level": 0, "avatar": "http://filestoresg1.beetalkmobile.com:8081/file/943886761143588291", "name": "\u5c0f\u90c1"}, "content": "\u5b83\u5011\u79c1\u5954\u4e86\u2026\u2026", "urls": [], "replies": {"first": [{"content": "\u5657\u2026\u90fd\u662f\u516c\u7684(\u256f\u0437\u2570)", "reply": "", "id": 8830308, "name": "J J "}], "last": [], "noMoreReplies": true}, "images": [], "id": 13771861}]}
