{"noMoreComments": true, "cursorEnd": 0, "id": "1432779", "comments": [{"postBy": {"location": "\u53f0\u4e2d\u5e02\u00b7\u53f0\u7063", "utc": 1433692041000, "level": 0, "avatar": "http://filestoresg1.beetalkmobile.com:8081/file/-5453664532729437189", "name": "\u9673\u745e\u7965"}, "content": "\u53ef\u662f\u6211\u6389\u7684\u662fi6", "urls": [], "replies": {"first": [{"content": "\u5230\u8b66\u5bdf\u5c40\u5831\u6848\u6216\u8a31\u80fd\u627e\u56de\u4f86\ud83d\ude05", "reply": "", "id": 8315748, "name": " fang"}], "last": [], "noMoreReplies": true}, "images": [], "id": 12939718}, {"postBy": {"location": "\u5c4f\u6771\u7e23\u00b7\u53f0\u7063", "utc": 1433692133000, "level": 0, "avatar": "http://filestoresg1.beetalkmobile.com:8081/file/9049445799499525274", "name": "\u744b"}, "content": "^^", "urls": [], "replies": {"first": [], "last": [], "noMoreReplies": true}, "images": ["http://filestoresg1.beetalkmobile.com:8081/file/7bbb9ab69213a994ce8d25a60b22daef"], "id": 12939821}, {"postBy": {"location": "\u5609\u7fa9\u5e02\u00b7\u53f0\u7063", "utc": 1433692217000, "level": 0, "avatar": "http://filestoresg1.beetalkmobile.com:8081/file/-909779892378697612", "name": "\u660e"}, "content": "\u6700\u8fd1\u5f88\u591a\u4eba\u90fd\u641e\u907a\u5931\u7684\uff0c\u904a\u6c11\u8b8a\u591a\u4e86.....", "urls": [], "replies": {"first": [{"content": "\u54c8\u54c8\u6211\u8b8a\u904a\u6c11\u4e86\ud83d\ude04\ud83d\ude04", "reply": "", "id": 8315721, "name": " fang"}], "last": [{"content": "\u8b1d\u8a87\u734e\u4f46\u4e0d\u53ef\u611b\u54c8\u54c8", "reply": "", "id": 8315829, "name": " fang"}, {"content": "\u90a3\u9858\u610f\u7576\u670b\u53cb\u55ce\uff1f", "reply": " fang", "id": 8315867, "name": "\u660e"}], "noMoreReplies": false}, "images": [], "id": 12939934}, {"postBy": {"location": "\u53f0\u4e2d\u5e02\u00b7\u53f0\u7063", "utc": 1433692303000, "level": 0, "avatar": "http://filestoresg1.beetalkmobile.com:8081/file/5876287128344047872", "name": "Mr.Pai"}, "content": "\u73fe\u5728\u597d\u50cf\u4e0d\u662f\u9818\u8d70\uff1f<br />\u800c\u662f\u60f3\u8ddf\u8ab0\u8d70\uff1f", "urls": [], "replies": {"first": [{"content": "\ud83d\ude05\ud83d\ude05\ud83d\ude05", "reply": "", "id": 8315797, "name": " fang"}, {"content": "\u662f\u4e0d\uff1f \ud83d\ude31\ud83d\ude31\ud83d\ude31", "reply": " fang", "id": 8315869, "name": "Mr.Pai"}], "last": [], "noMoreReplies": true}, "images": [], "id": 12940053}, {"postBy": {"location": "\u65b0\u5317\u5e02\u00b7\u53f0\u7063", "utc": 1433692928000, "level": 0, "avatar": "http://filestoresg1.beetalkmobile.com:8081/file/-2384553746178138325", "name": "~\u4fca\u4ed4~"}, "content": "\u6211\u6389\u7684\u59b9\u4ed4\u600e\u9ebc\u6703\u5728\u9019\u908a\uff01\u8d95\u5feb\u8ddf\u6211\u56de\u5bb6\u3002\u5916\u9762\u58de\u4eba\u5f88\u591a\uff01", "urls": [], "replies": {"first": [], "last": [], "noMoreReplies": true}, "images": [], "id": 12940884}]}
